pyExceptions/__init__.py
pyExceptions-1.1.1.dist-info/LICENSE.md
pyExceptions-1.1.1.dist-info/METADATA
pyExceptions-1.1.1.dist-info/WHEEL
pyExceptions-1.1.1.dist-info/top_level.txt
pyExceptions-1.1.1.dist-info/RECORD
