Metadata-Version: 2.1
Name: pyExceptions
Version: 1.1.1
Summary: An exceptions base-class to derive more powerful exceptions.
Home-page: https://github.com/Paebbels/pyExceptions
Author: Patrick Lehmann
Author-email: Paebbels@gmail.com
License: UNKNOWN
Project-URL: Documentation, https://pyExceptions.readthedocs.io/en/latest/
Project-URL: Source Code, https://github.com/Paebbels/pyExceptions
Project-URL: Issue Tracker, https://github.com/Paebbels/pyExceptions/issues
Keywords: Python3 Exceptions
Platform: UNKNOWN
Classifier: License :: OSI Approved :: Apache Software License
Classifier: Operating System :: OS Independent
Classifier: Programming Language :: Python :: 3 :: Only
Classifier: Programming Language :: Python :: 3.6
Classifier: Programming Language :: Python :: 3.7
Classifier: Programming Language :: Python :: 3.8
Classifier: Programming Language :: Python :: 3.9
Classifier: Development Status :: 5 - Production/Stable
Classifier: Intended Audience :: Developers
Classifier: Topic :: Utilities
Requires-Python: >=3.6
Requires-Dist: pydecor (>=2.0.1)
Requires-Dist: SphinxExtensions (>=0.2.0)
